[{"dni": "87654321", "legajo": "44", "apellido_nombre": "Gomez, Ana Maria", "domicilio": "Avenida Ficticia 742"}, {"dni": "23456789", "legajo": "7", "apellido_nombre": "Lopez, Maria Isabel", "domicilio": "Calle Luna 456"}, {"dni": "32334566", "legajo": "2", "apellido_nombre": "Romano, Salvador", "domicilio": "San Martin 55"}, {"dni": "45678901", "legajo": "12", "apellido_nombre": "Martinez, Juan Carlos", "domicilio": "Boulevard Central 123"}, {"dni": "89012345", "legajo": "31", "apellido_nombre": "Fernandez, Carlos Alberto", "domicilio": "Avenida del Sol 789"}, {"dni": "12345678", "legajo": "9", "apellido_nombre": "Gonzalez, Marcelo Alejandro", "domicilio": "Avenida Primavera 987"}, {"dni": "67890123", "legajo": "5", "apellido_nombre": "Diaz, Patricia Lorena", "domicilio": "Callej\u00c3\u00b3n Estrecho 654"}, {"dni": "45671234", "legajo": "23", "apellido_nombre": "Perez, Ramon Eduardo", "domicilio": "Pasaje del Norte 231"}, {"dni": "89098765", "legajo": "8", "apellido_nombre": "Sanchez, Carolina Andrea", "domicilio": "Avenida Rivadavia 876"}, {"dni": "67893456", "legajo": "3", "apellido_nombre": "Torres, Paula Alejandra", "domicilio": "Pasaje Sure\u00c3\u00b1o 789"}, {"dni": "78901234", "legajo": "10", "apellido_nombre": "Acosta, Sergio Martin", "domicilio": "Avenida Oeste 456"}, {"dni": "32109876", "legajo": "27", "apellido_nombre": "Suarez, Carolina Mariana", "domicilio": "Callejuela Escondida 876"}, {"dni": "89087654", "legajo": "4", "apellido_nombre": "Luna, Federico Juan", "domicilio": "Boulevard Sur 654"}, {"dni": "23456701", "legajo": "19", "apellido_nombre": "Mendoza, Maria Laura", "domicilio": "Avenida Este 543"}, {"dni": "56789012", "legajo": "11", "apellido_nombre": "Silva, Patricia Gabriela", "domicilio": "Ruta Vieja 987"}, {"dni": "10987654", "legajo": "28", "apellido_nombre": "Rios, Marcos Alejandro", "domicilio": "Calle Larga 654"}, {"dni": "43210987", "legajo": "14", "apellido_nombre": "Aguirre, Marina Beatriz", "domicilio": "Avenida Grande 321"}, {"dni": "76543210", "legajo": "20", "apellido_nombre": "Vega, Ignacio Emanuel", "domicilio": "Calle Ancha 789"}, {"dni": "21098765", "legajo": "1", "apellido_nombre": "Blanco, Silvia Adriana", "domicilio": "Pasaje Peque\u00c3\u00b1o 234"}, {"dni": "54321098", "legajo": "22", "apellido_nombre": "Moreno, Jorge Alberto", "domicilio": "Avenida Luminosa 567"}, {"dni": "98765432", "legajo": "21", "apellido_nombre": "Ibanez, Lucia Carolina", "domicilio": "Avenida Tranquila 432"}, {"dni": "34567890", "legajo": "26", "apellido_nombre": "Cabrera, Esteban Miguel", "domicilio": "Calle Silenciosa 109"}]